simpycard/__init__.py
simpycard/simpycard.py
simpycard-0.0.2.dist-info/LICENSE
simpycard-0.0.2.dist-info/METADATA
simpycard-0.0.2.dist-info/WHEEL
simpycard-0.0.2.dist-info/top_level.txt
simpycard-0.0.2.dist-info/RECORD
