Metadata-Version: 2.1
Name: simpycard
Version: 0.0.2
Summary: Package for simple playing-cards
Home-page: https://github.com/crazy6973/simpycard/
Author: crazy6973
License: UNKNOWN
Platform: UNKNOWN
Classifier: Programming Language :: Python :: 3.6
Classifier: License :: OSI Approved :: GNU General Public License v3 (GPLv3)
